{
  "day": 3,
  "topic": "Imperative Sentences",
  "totalDrills": 8,
  "drills": [
    {
      "id": 1,
      "type": "repeat-and-speak",
      "title": "Imperative Sentences — Speaking Set 1",
      "sentences": [
        {
          "english": "Close the door.",
          "hindi": "दरवाज़ा बंद करो।",
          "pronunciation": "close the door"
        },
        {
          "english": "Help me.",
          "hindi": "मेरी मदद करो।",
          "pronunciation": "help me"
        },
        {
          "english": "Drink plenty of water.",
          "hindi": "खूब पानी पियो।",
          "pronunciation": "drink plenty of water"
        }
      ]
    },
    {
      "id": 2,
      "type": "repeat-and-speak",
      "title": "Imperative Sentences — Speaking Set 2",
      "sentences": [
        {
          "english": "Stay away from fire.",
          "hindi": "आग से दूर रहो।",
          "pronunciation": "stay away from fire"
        },
        {
          "english": "Let's go for a walk.",
          "hindi": "चलो घूमने चलते हैं।",
          "pronunciation": "let's go for a walk"
        },
        {
          "english": "Open the door.",
          "hindi": "दरवाज़ा खोलो।",
          "pronunciation": "open the door"
        }
      ]
    },
    {
      "id": 3,
      "type": "repeat-and-speak",
      "title": "Imperative Sentences — Speaking Set 3",
      "sentences": [
        {
          "english": "Close the window.",
          "hindi": "खिड़की बंद करो।",
          "pronunciation": "close the window"
        },
        {
          "english": "Come here.",
          "hindi": "यहाँ आओ।",
          "pronunciation": "come here"
        },
        {
          "english": "Go there.",
          "hindi": "वहाँ जाओ।",
          "pronunciation": "go there"
        }
      ]
    },
    {
      "id": 4,
      "type": "repeat-and-speak",
      "title": "Imperative Sentences — Speaking Set 4",
      "sentences": [
        {
          "english": "Sit on the chair.",
          "hindi": "कुर्सी पर बैठो।",
          "pronunciation": "sit on the chair"
        },
        {
          "english": "Stand straight.",
          "hindi": "सीधे खड़े हो।",
          "pronunciation": "stand straight"
        },
        {
          "english": "Read the book.",
          "hindi": "किताब पढ़ो।",
          "pronunciation": "read the book"
        }
      ]
    },
    {
      "id": 5,
      "type": "repeat-and-speak",
      "title": "Imperative Sentences — Speaking Set 5",
      "sentences": [
        {
          "english": "Write your name.",
          "hindi": "अपना नाम लिखो।",
          "pronunciation": "write your name"
        },
        {
          "english": "Listen carefully.",
          "hindi": "ध्यान से सुनो।",
          "pronunciation": "listen carefully"
        },
        {
          "english": "Look at the board.",
          "hindi": "बोर्ड देखो।",
          "pronunciation": "look at the board"
        }
      ]
    },
    {
      "id": 6,
      "type": "repeat-and-speak",
      "title": "Imperative Sentences — Speaking Set 6",
      "sentences": [
        {
          "english": "Stop.",
          "hindi": "रुको।",
          "pronunciation": "stop"
        },
        {
          "english": "Bring water.",
          "hindi": "पानी लाओ।",
          "pronunciation": "bring water"
        },
        {
          "english": "Take this book.",
          "hindi": "यह किताब लो।",
          "pronunciation": "take this book"
        }
      ]
    },
    {
      "id": 7,
      "type": "repeat-and-speak",
      "title": "Imperative Sentences — Speaking Set 7",
      "sentences": [
        {
          "english": "Give me the pen.",
          "hindi": "मुझे कलम दो।",
          "pronunciation": "give me the pen"
        },
        {
          "english": "Keep your things.",
          "hindi": "अपना सामान रखो।",
          "pronunciation": "keep your things"
        },
        {
          "english": "Put it here.",
          "hindi": "यहाँ रखो।",
          "pronunciation": "put it here"
        }
      ]
    },
    {
      "id": 8,
      "type": "repeat-and-speak",
      "title": "Imperative Sentences — Speaking Set 8",
      "sentences": [
        {
          "english": "Move aside.",
          "hindi": "साइड हटो।",
          "pronunciation": "move aside"
        },
        {
          "english": "Run fast.",
          "hindi": "जल्दी दौड़ो।",
          "pronunciation": "run fast"
        },
        {
          "english": "Be quiet.",
          "hindi": "शांत रहो।",
          "pronunciation": "be quiet"
        }
      ]
    }
  ]
}
