{
  "day": 11,
  "title": "Use of Want",
  "totalWords": 25,
  "words": [
    {
      "id": 1,
      "word": "water",
      "hindi": "पानी चाहिए।",
      "simpleMeaning": "Used in the sentence: \"I want water.\"",
      "ipa": "",
      "sentences": {
        "daily": "I want water.",
        "office": "I want water.",
        "interview": "I want water."
      },
      "usageNote": "Appears with Use of Want",
      "cefrLevel": "A2-B1"
    },
    {
      "id": 2,
      "word": "home",
      "hindi": "जाना है।",
      "simpleMeaning": "Used in the sentence: \"I want to go home.\"",
      "ipa": "",
      "sentences": {
        "daily": "I want to go home.",
        "office": "I want to go home.",
        "interview": "I want to go home."
      },
      "usageNote": "Appears with Use of Want",
      "cefrLevel": "A2-B1"
    },
    {
      "id": 3,
      "word": "job",
      "hindi": "चाहता है।",
      "simpleMeaning": "Used in the sentence: \"He wants a new job.\"",
      "ipa": "",
      "sentences": {
        "daily": "He wants a new job.",
        "office": "He wants a new job.",
        "interview": "He wants a new job."
      },
      "usageNote": "Appears with Use of Want",
      "cefrLevel": "A2-B1"
    },
    {
      "id": 4,
      "word": "english",
      "hindi": "चाहती है।",
      "simpleMeaning": "Used in the sentence: \"She wants to learn English.\"",
      "ipa": "",
      "sentences": {
        "daily": "She wants to learn English.",
        "office": "She wants to learn English.",
        "interview": "She wants to learn English."
      },
      "usageNote": "Appears with Use of Want",
      "cefrLevel": "A2-B1"
    },
    {
      "id": 5,
      "word": "house",
      "hindi": "चाहते हैं।",
      "simpleMeaning": "Used in the sentence: \"We want a big house.\"",
      "ipa": "",
      "sentences": {
        "daily": "We want a big house.",
        "office": "We want a big house.",
        "interview": "We want a big house."
      },
      "usageNote": "Appears with Use of Want",
      "cefrLevel": "A2-B1"
    },
    {
      "id": 6,
      "word": "project",
      "hindi": "चाहते हैं।",
      "simpleMeaning": "Used in the sentence: \"They want to finish this project.\"",
      "ipa": "",
      "sentences": {
        "daily": "They want to finish this project.",
        "office": "They want to finish this project.",
        "interview": "They want to finish this project."
      },
      "usageNote": "Appears with Use of Want",
      "cefrLevel": "A2-B1"
    },
    {
      "id": 7,
      "word": "tea",
      "hindi": "चाय चाहिए?",
      "simpleMeaning": "Used in the sentence: \"Do you want tea?\"",
      "ipa": "",
      "sentences": {
        "daily": "Do you want tea?",
        "office": "Do you want tea?",
        "interview": "Do you want tea?"
      },
      "usageNote": "Appears with Use of Want",
      "cefrLevel": "A2-B1"
    },
    {
      "id": 8,
      "word": "book",
      "hindi": "नहीं चाहिए।",
      "simpleMeaning": "Used in the sentence: \"I do not want this book.\"",
      "ipa": "",
      "sentences": {
        "daily": "I do not want this book.",
        "office": "I do not want this book.",
        "interview": "I do not want this book."
      },
      "usageNote": "Appears with Use of Want",
      "cefrLevel": "A2-B1"
    },
    {
      "id": 9,
      "word": "me",
      "hindi": "चाहता है।",
      "simpleMeaning": "Used in the sentence: \"He wants to talk to me.\"",
      "ipa": "",
      "sentences": {
        "daily": "He wants to talk to me.",
        "office": "He wants to talk to me.",
        "interview": "He wants to talk to me."
      },
      "usageNote": "Appears with Use of Want",
      "cefrLevel": "A2-B1"
    },
    {
      "id": 10,
      "word": "rest",
      "hindi": "आराम चाहिए।",
      "simpleMeaning": "Used in the sentence: \"I want some rest.\"",
      "ipa": "",
      "sentences": {
        "daily": "I want some rest.",
        "office": "I want some rest.",
        "interview": "I want some rest."
      },
      "usageNote": "Appears with Use of Want",
      "cefrLevel": "A2-B1"
    },
    {
      "id": 11,
      "word": "coffee",
      "hindi": "चाहते हैं?",
      "simpleMeaning": "Used in the sentence: \"Do you want coffee?\"",
      "ipa": "",
      "sentences": {
        "daily": "Do you want coffee?",
        "office": "Do you want coffee?",
        "interview": "Do you want coffee?"
      },
      "usageNote": "Appears with Use of Want",
      "cefrLevel": "A2-B1"
    },
    {
      "id": 12,
      "word": "doctor",
      "hindi": "चाहती है।",
      "simpleMeaning": "Used in the sentence: \"She wants to become a doctor.\"",
      "ipa": "",
      "sentences": {
        "daily": "She wants to become a doctor.",
        "office": "She wants to become a doctor.",
        "interview": "She wants to become a doctor."
      },
      "usageNote": "Appears with Use of Want",
      "cefrLevel": "A2-B1"
    },
    {
      "id": 13,
      "word": "information",
      "hindi": "जानकारी चाहिए।",
      "simpleMeaning": "Used in the sentence: \"We want more information.\"",
      "ipa": "",
      "sentences": {
        "daily": "We want more information.",
        "office": "We want more information.",
        "interview": "We want more information."
      },
      "usageNote": "Appears with Use of Want",
      "cefrLevel": "A2-B1"
    },
    {
      "id": 14,
      "word": "help",
      "hindi": "चाहता हूँ।",
      "simpleMeaning": "Used in the sentence: \"I want your help.\"",
      "ipa": "",
      "sentences": {
        "daily": "I want your help.",
        "office": "I want your help.",
        "interview": "I want your help."
      },
      "usageNote": "Appears with Use of Want",
      "cefrLevel": "A2-B1"
    },
    {
      "id": 15,
      "word": "peace",
      "hindi": "चाहते हैं।",
      "simpleMeaning": "Used in the sentence: \"They want peace.\"",
      "ipa": "",
      "sentences": {
        "daily": "They want peace.",
        "office": "They want peace.",
        "interview": "They want peace."
      },
      "usageNote": "Appears with Use of Want",
      "cefrLevel": "A2-B1"
    },
    {
      "id": 16,
      "word": "quickly",
      "hindi": "करना है।",
      "simpleMeaning": "Used in the sentence: \"I want to finish this work quickly.\"",
      "ipa": "",
      "sentences": {
        "daily": "I want to finish this work quickly.",
        "office": "I want to finish this work quickly.",
        "interview": "I want to finish this work quickly."
      },
      "usageNote": "Appears with Use of Want",
      "cefrLevel": "A2-B1"
    },
    {
      "id": 17,
      "word": "promotion",
      "hindi": "चाहता है।",
      "simpleMeaning": "Used in the sentence: \"He wants a promotion.\"",
      "ipa": "",
      "sentences": {
        "daily": "He wants a promotion.",
        "office": "He wants a promotion.",
        "interview": "He wants a promotion."
      },
      "usageNote": "Appears with Use of Want",
      "cefrLevel": "A2-B1"
    },
    {
      "id": 18,
      "word": "outside",
      "hindi": "चाहते हो?",
      "simpleMeaning": "Used in the sentence: \"Do you want to go outside?\"",
      "ipa": "",
      "sentences": {
        "daily": "Do you want to go outside?",
        "office": "Do you want to go outside?",
        "interview": "Do you want to go outside?"
      },
      "usageNote": "Appears with Use of Want",
      "cefrLevel": "A2-B1"
    },
    {
      "id": 19,
      "word": "future",
      "hindi": "चाहते हैं।",
      "simpleMeaning": "Used in the sentence: \"We want a better future.\"",
      "ipa": "",
      "sentences": {
        "daily": "We want a better future.",
        "office": "We want a better future.",
        "interview": "We want a better future."
      },
      "usageNote": "Appears with Use of Want",
      "cefrLevel": "A2-B1"
    },
    {
      "id": 20,
      "word": "truth",
      "hindi": "जानना है।",
      "simpleMeaning": "Used in the sentence: \"I want to know the truth.\"",
      "ipa": "",
      "sentences": {
        "daily": "I want to know the truth.",
        "office": "I want to know the truth.",
        "interview": "I want to know the truth."
      },
      "usageNote": "Appears with Use of Want",
      "cefrLevel": "A2-B1"
    },
    {
      "id": 21,
      "word": "business",
      "hindi": "चाहती है।",
      "simpleMeaning": "Used in the sentence: \"She wants to start her own business.\"",
      "ipa": "",
      "sentences": {
        "daily": "She wants to start her own business.",
        "office": "She wants to start her own business.",
        "interview": "She wants to start her own business."
      },
      "usageNote": "Appears with Use of Want",
      "cefrLevel": "A2-B1"
    },
    {
      "id": 22,
      "word": "mistake",
      "hindi": "नहीं चाहिए।",
      "simpleMeaning": "Used in the sentence: \"I do not want any mistake.\"",
      "ipa": "",
      "sentences": {
        "daily": "I do not want any mistake.",
        "office": "I do not want any mistake.",
        "interview": "I do not want any mistake."
      },
      "usageNote": "Appears with Use of Want",
      "cefrLevel": "A2-B1"
    },
    {
      "id": 23,
      "word": "help",
      "hindi": "मदद चाहिए?",
      "simpleMeaning": "Used in the sentence: \"Do you want any help?\"",
      "ipa": "",
      "sentences": {
        "daily": "Do you want any help?",
        "office": "Do you want any help?",
        "interview": "Do you want any help?"
      },
      "usageNote": "Appears with Use of Want",
      "cefrLevel": "A2-B1"
    },
    {
      "id": 24,
      "word": "success",
      "hindi": "चाहते हैं।",
      "simpleMeaning": "Used in the sentence: \"They want success.\"",
      "ipa": "",
      "sentences": {
        "daily": "They want success.",
        "office": "They want success.",
        "interview": "They want success."
      },
      "usageNote": "Appears with Use of Want",
      "cefrLevel": "A2-B1"
    },
    {
      "id": 25,
      "word": "opportunity",
      "hindi": "मौका चाहिए।",
      "simpleMeaning": "Used in the sentence: \"I want this opportunity.\"",
      "ipa": "",
      "sentences": {
        "daily": "I want this opportunity.",
        "office": "I want this opportunity.",
        "interview": "I want this opportunity."
      },
      "usageNote": "Appears with Use of Want",
      "cefrLevel": "A2-B1"
    }
  ]
}
