{"day":31,"topic":{"title":"Revision","emoji":"🔄","cefr":"B1","difficulty":"intermediate","type":"revision"},"content":{"explanation":"\n**Revision Day 3 — Days 21-30 ka Complete Review:**\n\nआज हम पिछले 10 दिनों के सभी Advanced Modal Verbs का revision करेंगे।\n\n**Day 21: Used To** = पहले करता था\n\"I used to play cricket.\" (now I don't)\n\n**Day 22: Could** = Past ability / Polite request\n\"I could swim as a child.\" / \"Could you help me?\"\n\n**Day 23: Should Have** = काश किया होता\n\"I should have called earlier.\"\n\n**Day 24: Must Have** = ज़रूर हुआ होगा (99% certainty)\n\"He must have forgotten.\"\n\n**Day 25: Could Have** = हो सकता था (missed opportunity)\n\"I could have won.\"\n\n**Day 26: Would Have** = होता (imaginary past, 3rd conditional)\n\"If I had studied, I would have passed.\"\n\n**Day 27: May Have** = शायद हुआ हो (50% past possibility)\n\"She may have left already.\"\n\n**Day 28: Might Have** = शायद हुआ हो (30% — less certain)\n\"He might have taken a different route.\"\n\n**Day 29: Will / Shall** = Future tense\n\"I will come.\" / \"Shall we begin?\"\n\n**Day 30: Would / Ought To / Dare**\n\"Would you help?\" / \"You ought to be honest.\" / \"How dare you!\"\n  ","rules":["Used to + V1 = Past habit (no longer happening)","Could + V1 = Past ability; Could you? = Polite request","Should have / Could have / Would have / Must have + V3 = Perfect modals","Must have = 99% certain; May have = 50%; Might have = 30%","Would have + V3 = 3rd conditional (imaginary past)","Will + V1 = Future; Shall = formal offers/suggestions","Ought to + V1 = moral duty (must have \"to\" unlike other modals)"],"memoryTrick":"**Perfect Modal Formula: Subject + [Modal] + have + V3**\nMust have / Could have / Should have / Would have / May have / Might have — सब ने V3 चाहिए!","examples":[{"hindi":"मैं बचपन में बहुत तेज़ दौड़ता था।","english":"I used to run very fast in childhood.","type":"Day 21 — Used To"},{"hindi":"क्या आप यह document send कर सकते हैं?","english":"Could you please send this document?","type":"Day 22 — Could (polite)"},{"hindi":"मुझे पहले उसे inform करना चाहिए था।","english":"I should have informed him earlier.","type":"Day 23 — Should Have"},{"hindi":"वह ज़रूर बहुत busy रही होगी।","english":"She must have been very busy.","type":"Day 24 — Must Have"},{"hindi":"तुम कम से कम message कर सकते थे।","english":"You could have at least messaged.","type":"Day 25 — Could Have"},{"hindi":"अगर मैंने मेहनत की होती, तो pass हो जाता।","english":"If I had worked hard, I would have passed.","type":"Day 26 — Would Have"},{"hindi":"शायद उसने अभी तक reply नहीं किया हो।","english":"He may not have replied yet.","type":"Day 27 — May Have"},{"hindi":"वह शायद train miss कर गई हो।","english":"She might have missed the train.","type":"Day 28 — Might Have"}],"mistakes":[{"wrong":"I use to go there.","correct":"I used to go there.","why":"'Used to' (with -d) in positive sentences"},{"wrong":"He must have went.","correct":"He must have gone.","why":"Perfect modals always need V3 (past participle)"},{"wrong":"If I would have known, I would have helped.","correct":"If I had known, I would have helped.","why":"If clause = 'had + V3', not 'would have'"},{"wrong":"You ought respect elders.","correct":"You ought to respect elders.","why":"Ought TO + V1 — 'to' is always required"}],"speakingTips":["हर perfect modal पर 2 sentences बनाओ — आज 14 sentences का target रखो","Record करो और check करो कि V3 सही use हुई या नहीं","एक दोस्त के साथ roleplay करो — past situations discuss करो"]},"vocabulary":[{"id":1,"word":"Revise","hindi":"दोहराना","ipa":"","example":"Revise all modal verbs today."},{"id":2,"word":"Certainty","hindi":"निश्चितता","ipa":"","example":"Must have = high certainty."},{"id":3,"word":"Possibility","hindi":"संभावना","ipa":"","example":"May have = 50% possibility."},{"id":4,"word":"Obligation","hindi":"दायित्व","ipa":"","example":"Ought to = moral obligation."},{"id":5,"word":"Habit","hindi":"आदत","ipa":"","example":"I used to have good habits."},{"id":6,"word":"Conditional","hindi":"शर्त वाला","ipa":"","example":"Would have = conditional past."}],"practice":[{"id":"d31-001","hindi":"मैं बहुत थका हुआ हूँ।","english":"I am very tired.","alternatives":["i am very tired.","i am so tired."],"hint":"I am + adjective","explanation":""},{"id":"d31-002","hindi":"वह एक अच्छा इंसान है।","english":"He is a good person.","alternatives":["he is a very good person."],"hint":"He is + article + adjective + noun","explanation":""},{"id":"d31-003","hindi":"हम सब यहाँ हैं।","english":"We are all here.","alternatives":["we all are here."],"hint":"We are + all + adjective","explanation":""},{"id":"d31-004","hindi":"कल मौसम बहुत ठंडा था।","english":"Yesterday the weather was very cold.","alternatives":["the weather was very cold yesterday."],"hint":"was + adjective (past)","explanation":""},{"id":"d31-005","hindi":"वे लोग बाज़ार में थे।","english":"They were in the market.","alternatives":["they were at the market."],"hint":"They were + in/at + place","explanation":""},{"id":"d31-006","hindi":"मेरे पास एक स्मार्टफोन है।","english":"I have a smartphone.","alternatives":["i have got a smartphone."],"hint":"I have + article + noun","explanation":""},{"id":"d31-007","hindi":"उसके पास तीन बिल्लियाँ हैं।","english":"She has three cats.","alternatives":["she has got three cats."],"hint":"She has + number + noun","explanation":""},{"id":"d31-008","hindi":"क्या तुम्हारे पास समय है?","english":"Do you have time?","alternatives":["do you have any time?","have you got time?"],"hint":"Do you have + noun?","explanation":""},{"id":"d31-009","hindi":"मेरे पास पहले एक साइकिल थी।","english":"I had a bicycle before.","alternatives":["i used to have a bicycle."],"hint":"I had + article + noun + before","explanation":""},{"id":"d31-010","hindi":"जब वह स्टेशन पहुँचा, ट्रेन जा चुकी थी।","english":"When he reached the station, the train had already left.","alternatives":["by the time he reached, the train had left."],"hint":"Past Perfect: had + past participle","explanation":""},{"id":"d31-011","hindi":"मैं तैर सकता हूँ।","english":"I can swim.","alternatives":["i am able to swim."],"hint":"can + base verb","explanation":""},{"id":"d31-012","hindi":"तुम्हें रोज़ व्यायाम करना चाहिए।","english":"You should exercise every day.","alternatives":["you should exercise daily."],"hint":"should + base verb","explanation":""},{"id":"d31-013","hindi":"शायद कल बारिश होगी।","english":"It may rain tomorrow.","alternatives":["it might rain tomorrow."],"hint":"may/might + base verb","explanation":""},{"id":"d31-014","hindi":"तुम्हें अभी जाना चाहिए।","english":"You must go now.","alternatives":["you should go now."],"hint":"must + base verb","explanation":""},{"id":"d31-015","hindi":"क्या मैं यहाँ बैठ सकता हूँ?","english":"May I sit here?","alternatives":["can i sit here?"],"hint":"May I + verb?","explanation":""},{"id":"d31-016","hindi":"मुझे पहले यह करना था।","english":"I should have done this earlier.","alternatives":["i ought to have done this before."],"hint":"should have + past participle","explanation":""},{"id":"d31-017","hindi":"वह ज़रूर यहाँ आया होगा।","english":"He must have come here.","alternatives":["he must have visited here."],"hint":"must have + past participle","explanation":""},{"id":"d31-018","hindi":"काश मैंने यह पहले सीखा होता।","english":"I wish I had learned this earlier.","alternatives":["i wish i had studied this before."],"hint":"I wish + had + past participle","explanation":""},{"id":"d31-019","hindi":"मैं एक नई नौकरी चाहता हूँ।","english":"I want a new job.","alternatives":["i want to find a new job."],"hint":"I want + noun/to + verb","explanation":""},{"id":"d31-020","hindi":"मुझे जाने दो।","english":"Let me go.","alternatives":["please let me go."],"hint":"Let + me + base verb","explanation":""},{"id":"d31-021","hindi":"चलो बाहर खाना खाते हैं।","english":"Let's eat out.","alternatives":["let's go out to eat.","let's have food outside."],"hint":"Let's + base verb","explanation":""},{"id":"d31-022","hindi":"मैं एक कप चाय लेना चाहूँगा।","english":"I would like to have a cup of tea.","alternatives":["i would like a cup of tea."],"hint":"would like to + base verb","explanation":""},{"id":"d31-023","hindi":"मुझे पहले यह पसंद था।","english":"I used to like this.","alternatives":["i used to enjoy this."],"hint":"used to + base verb","explanation":""},{"id":"d31-024","hindi":"वह पहले बहुत तेज़ दौड़ सकता था।","english":"He could run very fast before.","alternatives":["he was able to run fast before."],"hint":"could + base verb","explanation":""},{"id":"d31-025","hindi":"शायद वह कल आ सकती है।","english":"She could come tomorrow.","alternatives":["she might come tomorrow."],"hint":"could + base verb (possibility)","explanation":""},{"id":"d31-026","hindi":"तुम्हें डॉक्टर से मिलना होगा।","english":"You will have to see a doctor.","alternatives":["you must see a doctor."],"hint":"will have to + base verb","explanation":""},{"id":"d31-027","hindi":"हमें कड़ी मेहनत करनी चाहिए।","english":"We ought to work hard.","alternatives":["we should work hard."],"hint":"ought to + base verb","explanation":""},{"id":"d31-028","hindi":"वह जाने की हिम्मत नहीं कर सका।","english":"He dared not go.","alternatives":["he did not dare to go."],"hint":"dare + not + base verb","explanation":""},{"id":"d31-029","hindi":"मुझे पानी चाहिए।","english":"I need water.","alternatives":["i want some water."],"hint":"I need + noun","explanation":""},{"id":"d31-030","hindi":"क्या तुम मेरी मदद करना चाहोगे?","english":"Would you like to help me?","alternatives":["would you help me?"],"hint":"Would you like to + verb?","explanation":""},{"id":"d31-031","hindi":"मैं अंग्रेज़ी में बात करना सीख रहा हूँ।","english":"I am learning to speak in English.","alternatives":["i am learning to talk in english."],"hint":"I am + verb+ing + to + verb","explanation":""},{"id":"d31-032","hindi":"वह हर सुबह योग करता है।","english":"He does yoga every morning.","alternatives":["he practices yoga every morning."],"hint":"He does + noun + every morning","explanation":""},{"id":"d31-033","hindi":"मुझे समझ नहीं आया।","english":"I did not understand.","alternatives":["i didn't understand.","i could not understand."],"hint":"I did not + base verb","explanation":""},{"id":"d31-034","hindi":"हम कल दिल्ली जाएँगे।","english":"We will go to Delhi tomorrow.","alternatives":["we are going to delhi tomorrow."],"hint":"will + base verb + tomorrow","explanation":""},{"id":"d31-035","hindi":"उसने मुझसे माफ़ी माँगी।","english":"He apologized to me.","alternatives":["he said sorry to me."],"hint":"He + past verb + to me","explanation":""},{"id":"d31-036","hindi":"क्या तुम खुश हो?","english":"Are you happy?","alternatives":["are you feeling happy?"],"hint":"Are you + adjective?","explanation":""},{"id":"d31-037","hindi":"बच्चे पार्क में खेल रहे थे।","english":"The children were playing in the park.","alternatives":["children were playing in park."],"hint":"were + verb+ing (past continuous)","explanation":""},{"id":"d31-038","hindi":"मैं यह काम तीन घंटे से कर रहा हूँ।","english":"I have been doing this work for three hours.","alternatives":["i have been working on this for three hours."],"hint":"have been + verb+ing + for + time","explanation":""},{"id":"d31-039","hindi":"उसने मुझे कभी धोखा नहीं दिया।","english":"He never cheated me.","alternatives":["he has never cheated me.","he never deceived me."],"hint":"never + past verb","explanation":""},{"id":"d31-040","hindi":"मैं तुमसे सहमत हूँ।","english":"I agree with you.","alternatives":["i agree with you."],"hint":"I agree with + you","explanation":""}],"mockTest":[{"id":"d31-001-test","hindi":"मैं बहुत थका हुआ हूँ।","english":"I am very tired.","alternatives":["i am very tired.","i am so tired."]},{"id":"d31-002-test","hindi":"वह एक अच्छा इंसान है।","english":"He is a good person.","alternatives":["he is a very good person."]},{"id":"d31-003-test","hindi":"हम सब यहाँ हैं।","english":"We are all here.","alternatives":["we all are here."]},{"id":"d31-004-test","hindi":"कल मौसम बहुत ठंडा था।","english":"Yesterday the weather was very cold.","alternatives":["the weather was very cold yesterday."]},{"id":"d31-005-test","hindi":"वे लोग बाज़ार में थे।","english":"They were in the market.","alternatives":["they were at the market."]},{"id":"d31-006-test","hindi":"मेरे पास एक स्मार्टफोन है।","english":"I have a smartphone.","alternatives":["i have got a smartphone."]},{"id":"d31-007-test","hindi":"उसके पास तीन बिल्लियाँ हैं।","english":"She has three cats.","alternatives":["she has got three cats."]},{"id":"d31-008-test","hindi":"क्या तुम्हारे पास समय है?","english":"Do you have time?","alternatives":["do you have any time?","have you got time?"]},{"id":"d31-009-test","hindi":"मेरे पास पहले एक साइकिल थी।","english":"I had a bicycle before.","alternatives":["i used to have a bicycle."]},{"id":"d31-010-test","hindi":"जब वह स्टेशन पहुँचा, ट्रेन जा चुकी थी।","english":"When he reached the station, the train had already left.","alternatives":["by the time he reached, the train had left."]},{"id":"d31-011-test","hindi":"मैं तैर सकता हूँ।","english":"I can swim.","alternatives":["i am able to swim."]},{"id":"d31-012-test","hindi":"तुम्हें रोज़ व्यायाम करना चाहिए।","english":"You should exercise every day.","alternatives":["you should exercise daily."]},{"id":"d31-013-test","hindi":"शायद कल बारिश होगी।","english":"It may rain tomorrow.","alternatives":["it might rain tomorrow."]},{"id":"d31-014-test","hindi":"तुम्हें अभी जाना चाहिए।","english":"You must go now.","alternatives":["you should go now."]},{"id":"d31-015-test","hindi":"क्या मैं यहाँ बैठ सकता हूँ?","english":"May I sit here?","alternatives":["can i sit here?"]},{"id":"d31-016-test","hindi":"मुझे पहले यह करना था।","english":"I should have done this earlier.","alternatives":["i ought to have done this before."]},{"id":"d31-017-test","hindi":"वह ज़रूर यहाँ आया होगा।","english":"He must have come here.","alternatives":["he must have visited here."]},{"id":"d31-018-test","hindi":"काश मैंने यह पहले सीखा होता।","english":"I wish I had learned this earlier.","alternatives":["i wish i had studied this before."]},{"id":"d31-019-test","hindi":"मैं एक नई नौकरी चाहता हूँ।","english":"I want a new job.","alternatives":["i want to find a new job."]},{"id":"d31-020-test","hindi":"मुझे जाने दो।","english":"Let me go.","alternatives":["please let me go."]},{"id":"d31-021-test","hindi":"चलो बाहर खाना खाते हैं।","english":"Let's eat out.","alternatives":["let's go out to eat.","let's have food outside."]},{"id":"d31-022-test","hindi":"मैं एक कप चाय लेना चाहूँगा।","english":"I would like to have a cup of tea.","alternatives":["i would like a cup of tea."]},{"id":"d31-023-test","hindi":"मुझे पहले यह पसंद था।","english":"I used to like this.","alternatives":["i used to enjoy this."]},{"id":"d31-024-test","hindi":"वह पहले बहुत तेज़ दौड़ सकता था।","english":"He could run very fast before.","alternatives":["he was able to run fast before."]},{"id":"d31-025-test","hindi":"शायद वह कल आ सकती है।","english":"She could come tomorrow.","alternatives":["she might come tomorrow."]},{"id":"d31-026-test","hindi":"तुम्हें डॉक्टर से मिलना होगा।","english":"You will have to see a doctor.","alternatives":["you must see a doctor."]},{"id":"d31-027-test","hindi":"हमें कड़ी मेहनत करनी चाहिए।","english":"We ought to work hard.","alternatives":["we should work hard."]},{"id":"d31-028-test","hindi":"वह जाने की हिम्मत नहीं कर सका।","english":"He dared not go.","alternatives":["he did not dare to go."]},{"id":"d31-029-test","hindi":"मुझे पानी चाहिए।","english":"I need water.","alternatives":["i want some water."]},{"id":"d31-030-test","hindi":"क्या तुम मेरी मदद करना चाहोगे?","english":"Would you like to help me?","alternatives":["would you help me?"]},{"id":"d31-031-test","hindi":"मैं अंग्रेज़ी में बात करना सीख रहा हूँ।","english":"I am learning to speak in English.","alternatives":["i am learning to talk in english."]},{"id":"d31-032-test","hindi":"वह हर सुबह योग करता है।","english":"He does yoga every morning.","alternatives":["he practices yoga every morning."]},{"id":"d31-033-test","hindi":"मुझे समझ नहीं आया।","english":"I did not understand.","alternatives":["i didn't understand.","i could not understand."]},{"id":"d31-034-test","hindi":"हम कल दिल्ली जाएँगे।","english":"We will go to Delhi tomorrow.","alternatives":["we are going to delhi tomorrow."]},{"id":"d31-035-test","hindi":"उसने मुझसे माफ़ी माँगी।","english":"He apologized to me.","alternatives":["he said sorry to me."]},{"id":"d31-036-test","hindi":"क्या तुम खुश हो?","english":"Are you happy?","alternatives":["are you feeling happy?"]},{"id":"d31-037-test","hindi":"बच्चे पार्क में खेल रहे थे।","english":"The children were playing in the park.","alternatives":["children were playing in park."]},{"id":"d31-038-test","hindi":"मैं यह काम तीन घंटे से कर रहा हूँ।","english":"I have been doing this work for three hours.","alternatives":["i have been working on this for three hours."]},{"id":"d31-039-test","hindi":"उसने मुझे कभी धोखा नहीं दिया।","english":"He never cheated me.","alternatives":["he has never cheated me.","he never deceived me."]},{"id":"d31-040-test","hindi":"मैं तुमसे सहमत हूँ।","english":"I agree with you.","alternatives":["i agree with you."]}]}