{
  "day": 35,
  "topic": "Tenses Part 4 — Mixed Tense Practice (All 12 Tenses)",
  "totalQuestions": 20,
  "questions": [
    {
      "id": 1,
      "hindi": "मैं चावल खाता हूँ।",
      "english": "I eat rice.",
      "alternatives": [],
      "hint": "Use the pattern: Review and mix all Present, Past, and Future tense forms in one set of exercises",
      "explanation": "Correct sentence: \"I eat rice.\"",
      "difficulty": "easy",
      "tags": [
        "tenses"
      ],
      "grammarRule": "Tenses Part 4 — Mixed Tense Practice (All 12 Tenses)",
      "category": "Tenses Part 4 — Mixed Tense Practice (All 12 Tenses) practice"
    },
    {
      "id": 2,
      "hindi": "मैं चावल खा रहा हूँ।",
      "english": "I am eating rice.",
      "alternatives": [],
      "hint": "Use the pattern: Review and mix all Present, Past, and Future tense forms in one set of exercises",
      "explanation": "Correct sentence: \"I am eating rice.\"",
      "difficulty": "medium",
      "tags": [
        "tenses"
      ],
      "grammarRule": "Tenses Part 4 — Mixed Tense Practice (All 12 Tenses)",
      "category": "Tenses Part 4 — Mixed Tense Practice (All 12 Tenses) practice"
    },
    {
      "id": 3,
      "hindi": "मैंने चावल खाया है।",
      "english": "I have eaten rice.",
      "alternatives": [],
      "hint": "Use the pattern: Review and mix all Present, Past, and Future tense forms in one set of exercises",
      "explanation": "Correct sentence: \"I have eaten rice.\"",
      "difficulty": "hard",
      "tags": [
        "tenses"
      ],
      "grammarRule": "Tenses Part 4 — Mixed Tense Practice (All 12 Tenses)",
      "category": "Tenses Part 4 — Mixed Tense Practice (All 12 Tenses) practice"
    },
    {
      "id": 4,
      "hindi": "मैं एक घंटे से चावल खा रहा हूँ।",
      "english": "I have been eating rice for an hour.",
      "alternatives": [],
      "hint": "Use the pattern: Review and mix all Present, Past, and Future tense forms in one set of exercises",
      "explanation": "Correct sentence: \"I have been eating rice for an hour.\"",
      "difficulty": "easy",
      "tags": [
        "tenses"
      ],
      "grammarRule": "Tenses Part 4 — Mixed Tense Practice (All 12 Tenses)",
      "category": "Tenses Part 4 — Mixed Tense Practice (All 12 Tenses) practice"
    },
    {
      "id": 5,
      "hindi": "मैंने चावल खाया।",
      "english": "I ate rice.",
      "alternatives": [],
      "hint": "Use the pattern: Review and mix all Present, Past, and Future tense forms in one set of exercises",
      "explanation": "Correct sentence: \"I ate rice.\"",
      "difficulty": "medium",
      "tags": [
        "tenses"
      ],
      "grammarRule": "Tenses Part 4 — Mixed Tense Practice (All 12 Tenses)",
      "category": "Tenses Part 4 — Mixed Tense Practice (All 12 Tenses) practice"
    },
    {
      "id": 6,
      "hindi": "मैं चावल खा रहा था।",
      "english": "I was eating rice.",
      "alternatives": [],
      "hint": "Use the pattern: Review and mix all Present, Past, and Future tense forms in one set of exercises",
      "explanation": "Correct sentence: \"I was eating rice.\"",
      "difficulty": "hard",
      "tags": [
        "tenses"
      ],
      "grammarRule": "Tenses Part 4 — Mixed Tense Practice (All 12 Tenses)",
      "category": "Tenses Part 4 — Mixed Tense Practice (All 12 Tenses) practice"
    },
    {
      "id": 7,
      "hindi": "मैं चावल खा चुका था।",
      "english": "I had eaten rice.",
      "alternatives": [],
      "hint": "Use the pattern: Review and mix all Present, Past, and Future tense forms in one set of exercises",
      "explanation": "Correct sentence: \"I had eaten rice.\"",
      "difficulty": "easy",
      "tags": [
        "tenses"
      ],
      "grammarRule": "Tenses Part 4 — Mixed Tense Practice (All 12 Tenses)",
      "category": "Tenses Part 4 — Mixed Tense Practice (All 12 Tenses) practice"
    },
    {
      "id": 8,
      "hindi": "मैं एक घंटे से चावल खा रहा था।",
      "english": "I had been eating rice for an hour.",
      "alternatives": [],
      "hint": "Use the pattern: Review and mix all Present, Past, and Future tense forms in one set of exercises",
      "explanation": "Correct sentence: \"I had been eating rice for an hour.\"",
      "difficulty": "medium",
      "tags": [
        "tenses"
      ],
      "grammarRule": "Tenses Part 4 — Mixed Tense Practice (All 12 Tenses)",
      "category": "Tenses Part 4 — Mixed Tense Practice (All 12 Tenses) practice"
    },
    {
      "id": 9,
      "hindi": "मैं चावल खाऊँगा।",
      "english": "I will eat rice.",
      "alternatives": [],
      "hint": "Use the pattern: Review and mix all Present, Past, and Future tense forms in one set of exercises",
      "explanation": "Correct sentence: \"I will eat rice.\"",
      "difficulty": "hard",
      "tags": [
        "tenses"
      ],
      "grammarRule": "Tenses Part 4 — Mixed Tense Practice (All 12 Tenses)",
      "category": "Tenses Part 4 — Mixed Tense Practice (All 12 Tenses) practice"
    },
    {
      "id": 10,
      "hindi": "मैं चावल खा रहा होऊँगा।",
      "english": "I will be eating rice.",
      "alternatives": [],
      "hint": "Use the pattern: Review and mix all Present, Past, and Future tense forms in one set of exercises",
      "explanation": "Correct sentence: \"I will be eating rice.\"",
      "difficulty": "easy",
      "tags": [
        "tenses"
      ],
      "grammarRule": "Tenses Part 4 — Mixed Tense Practice (All 12 Tenses)",
      "category": "Tenses Part 4 — Mixed Tense Practice (All 12 Tenses) practice"
    },
    {
      "id": 11,
      "hindi": "मैं चावल खा चुका होऊँगा।",
      "english": "I will have eaten rice.",
      "alternatives": [],
      "hint": "Use the pattern: Review and mix all Present, Past, and Future tense forms in one set of exercises",
      "explanation": "Correct sentence: \"I will have eaten rice.\"",
      "difficulty": "medium",
      "tags": [
        "tenses"
      ],
      "grammarRule": "Tenses Part 4 — Mixed Tense Practice (All 12 Tenses)",
      "category": "Tenses Part 4 — Mixed Tense Practice (All 12 Tenses) practice"
    },
    {
      "id": 12,
      "hindi": "मैं एक घंटे से चावल खा रहा होऊँगा।",
      "english": "I will have been eating rice for an hour.",
      "alternatives": [],
      "hint": "Use the pattern: Review and mix all Present, Past, and Future tense forms in one set of exercises",
      "explanation": "Correct sentence: \"I will have been eating rice for an hour.\"",
      "difficulty": "hard",
      "tags": [
        "tenses"
      ],
      "grammarRule": "Tenses Part 4 — Mixed Tense Practice (All 12 Tenses)",
      "category": "Tenses Part 4 — Mixed Tense Practice (All 12 Tenses) practice"
    },
    {
      "id": 13,
      "hindi": "वह काम करती है।",
      "english": "She works.",
      "alternatives": [],
      "hint": "Use the pattern: Review and mix all Present, Past, and Future tense forms in one set of exercises",
      "explanation": "Correct sentence: \"She works.\"",
      "difficulty": "easy",
      "tags": [
        "tenses"
      ],
      "grammarRule": "Tenses Part 4 — Mixed Tense Practice (All 12 Tenses)",
      "category": "Tenses Part 4 — Mixed Tense Practice (All 12 Tenses) practice"
    },
    {
      "id": 14,
      "hindi": "वह काम कर रही है।",
      "english": "She is working.",
      "alternatives": [],
      "hint": "Use the pattern: Review and mix all Present, Past, and Future tense forms in one set of exercises",
      "explanation": "Correct sentence: \"She is working.\"",
      "difficulty": "medium",
      "tags": [
        "tenses"
      ],
      "grammarRule": "Tenses Part 4 — Mixed Tense Practice (All 12 Tenses)",
      "category": "Tenses Part 4 — Mixed Tense Practice (All 12 Tenses) practice"
    },
    {
      "id": 15,
      "hindi": "उसने काम कर लिया है।",
      "english": "She has worked.",
      "alternatives": [],
      "hint": "Use the pattern: Review and mix all Present, Past, and Future tense forms in one set of exercises",
      "explanation": "Correct sentence: \"She has worked.\"",
      "difficulty": "hard",
      "tags": [
        "tenses"
      ],
      "grammarRule": "Tenses Part 4 — Mixed Tense Practice (All 12 Tenses)",
      "category": "Tenses Part 4 — Mixed Tense Practice (All 12 Tenses) practice"
    },
    {
      "id": 16,
      "hindi": "वह दो घंटे से काम कर रही है।",
      "english": "She has been working for two hours.",
      "alternatives": [],
      "hint": "Use the pattern: Review and mix all Present, Past, and Future tense forms in one set of exercises",
      "explanation": "Correct sentence: \"She has been working for two hours.\"",
      "difficulty": "easy",
      "tags": [
        "tenses"
      ],
      "grammarRule": "Tenses Part 4 — Mixed Tense Practice (All 12 Tenses)",
      "category": "Tenses Part 4 — Mixed Tense Practice (All 12 Tenses) practice"
    },
    {
      "id": 17,
      "hindi": "उसने काम किया।",
      "english": "She worked.",
      "alternatives": [],
      "hint": "Use the pattern: Review and mix all Present, Past, and Future tense forms in one set of exercises",
      "explanation": "Correct sentence: \"She worked.\"",
      "difficulty": "medium",
      "tags": [
        "tenses"
      ],
      "grammarRule": "Tenses Part 4 — Mixed Tense Practice (All 12 Tenses)",
      "category": "Tenses Part 4 — Mixed Tense Practice (All 12 Tenses) practice"
    },
    {
      "id": 18,
      "hindi": "वह काम कर रही थी।",
      "english": "She was working.",
      "alternatives": [],
      "hint": "Use the pattern: Review and mix all Present, Past, and Future tense forms in one set of exercises",
      "explanation": "Correct sentence: \"She was working.\"",
      "difficulty": "hard",
      "tags": [
        "tenses"
      ],
      "grammarRule": "Tenses Part 4 — Mixed Tense Practice (All 12 Tenses)",
      "category": "Tenses Part 4 — Mixed Tense Practice (All 12 Tenses) practice"
    },
    {
      "id": 19,
      "hindi": "उसने काम कर लिया था।",
      "english": "She had worked.",
      "alternatives": [],
      "hint": "Use the pattern: Review and mix all Present, Past, and Future tense forms in one set of exercises",
      "explanation": "Correct sentence: \"She had worked.\"",
      "difficulty": "easy",
      "tags": [
        "tenses"
      ],
      "grammarRule": "Tenses Part 4 — Mixed Tense Practice (All 12 Tenses)",
      "category": "Tenses Part 4 — Mixed Tense Practice (All 12 Tenses) practice"
    },
    {
      "id": 20,
      "hindi": "वह दो घंटे से काम कर रही थी।",
      "english": "She had been working for two hours.",
      "alternatives": [],
      "hint": "Use the pattern: Review and mix all Present, Past, and Future tense forms in one set of exercises",
      "explanation": "Correct sentence: \"She had been working for two hours.\"",
      "difficulty": "medium",
      "tags": [
        "tenses"
      ],
      "grammarRule": "Tenses Part 4 — Mixed Tense Practice (All 12 Tenses)",
      "category": "Tenses Part 4 — Mixed Tense Practice (All 12 Tenses) practice"
    }
  ]
}
