{
  "day": 44,
  "title": "Need To / Needed To",
  "tagline": "Need To / Needed To को सही तरीके से समझें और बोलें।",
  "summary": "Need To / Needed To का सही उपयोग आपकी English को ज़्यादा natural और fluent बनाता है। Formula: Subject + need/needs to (present) / needed to (past) + base verb",
  "hindiSummary": "आज आप Need To / Needed To का सही उपयोग सीखेंगे — कब और कैसे इसे बोलचाल और लेखन में use करना है।",
  "whatYouWillLearn": [
    "Need To / Needed To की सही formula और structure",
    "Need To / Needed To के साथ positive, negative और question sentences",
    "Need To / Needed To का daily life और office में उपयोग",
    "Common mistakes जो लोग यहां करते हैं"
  ]
}
