{
  "day": 51,
  "title": "Reported Speech Part 1 — Statements",
  "slug": "51-reported-speech-part-1-statements",
  "type": "grammar",
  "difficulty": "intermediate",
  "cefr": "B1",
  "emoji": "🗣️",
  "color": "#3b82f6",
  "topics": [
    "Reported Speech Part 1 — Statements"
  ],
  "totalQuestions": 20,
  "totalVocabulary": 20,
  "estimatedTime": "2-3 hours",
  "xpReward": 200,
  "coinsReward": 30,
  "prerequisites": [
    50
  ],
  "nextDay": 52,
  "tags": [
    "grammar",
    "reported speech part 1 — statements"
  ],
  "lastUpdated": "2026-07-09",
  "version": "1.0"
}
