{
  "day": 66,
  "topic": "Colours & Judiciary Vocabulary",
  "totalDrills": 7,
  "drills": [
    {
      "id": 1,
      "type": "repeat-and-speak",
      "title": "Colours & Judiciary Vocabulary — Speaking Set 1",
      "sentences": [
        {
          "english": "Red colour is a symbol of danger.",
          "hindi": "लाल रंग खतरे का प्रतीक है।",
          "pronunciation": "red colour is a symbol of danger"
        },
        {
          "english": "The sky looks blue.",
          "hindi": "आसमान नीला दिखता है।",
          "pronunciation": "the sky looks blue"
        },
        {
          "english": "Green colour is a symbol of peace.",
          "hindi": "हरा रंग शांति का प्रतीक है।",
          "pronunciation": "green colour is a symbol of peace"
        }
      ]
    },
    {
      "id": 2,
      "type": "repeat-and-speak",
      "title": "Colours & Judiciary Vocabulary — Speaking Set 2",
      "sentences": [
        {
          "english": "He is wearing a yellow shirt.",
          "hindi": "उसने पीली शर्ट पहनी है।",
          "pronunciation": "he is wearing a yellow shirt"
        },
        {
          "english": "Everyone likes black colour.",
          "hindi": "काला रंग सबको पसंद है।",
          "pronunciation": "everyone likes black colour"
        },
        {
          "english": "White colour represents purity.",
          "hindi": "सफेद रंग शुद्धता दर्शाता है।",
          "pronunciation": "white colour represents purity"
        }
      ]
    },
    {
      "id": 3,
      "type": "repeat-and-speak",
      "title": "Colours & Judiciary Vocabulary — Speaking Set 3",
      "sentences": [
        {
          "english": "This flower is orange in colour.",
          "hindi": "यह फूल नारंगी रंग का है।",
          "pronunciation": "this flower is orange in colour"
        },
        {
          "english": "Purple colour is considered royal.",
          "hindi": "बैंगनी रंग शाही माना जाता है।",
          "pronunciation": "purple colour is considered royal"
        },
        {
          "english": "She likes pink colour a lot.",
          "hindi": "उसे गुलाबी रंग बहुत पसंद है।",
          "pronunciation": "she likes pink colour a lot"
        }
      ]
    },
    {
      "id": 4,
      "type": "repeat-and-speak",
      "title": "Colours & Judiciary Vocabulary — Speaking Set 4",
      "sentences": [
        {
          "english": "Brown coloured soil is fertile.",
          "hindi": "भूरे रंग की मिट्टी उपजाऊ होती है।",
          "pronunciation": "brown coloured soil is fertile"
        },
        {
          "english": "The hearing is going on in the court.",
          "hindi": "अदालत में सुनवाई चल रही है।",
          "pronunciation": "the hearing is going on in the court"
        },
        {
          "english": "The judge announced the verdict.",
          "hindi": "जज ने फैसला सुनाया।",
          "pronunciation": "the judge announced the verdict"
        }
      ]
    },
    {
      "id": 5,
      "type": "repeat-and-speak",
      "title": "Colours & Judiciary Vocabulary — Speaking Set 5",
      "sentences": [
        {
          "english": "The lawyer argued the case.",
          "hindi": "वकील ने बहस की।",
          "pronunciation": "the lawyer argued the case"
        },
        {
          "english": "The law is equal for everyone.",
          "hindi": "कानून सबके लिए समान है।",
          "pronunciation": "the law is equal for everyone"
        },
        {
          "english": "There should be no delay in justice.",
          "hindi": "न्याय में देरी नहीं होनी चाहिए।",
          "pronunciation": "there should be no delay in justice"
        }
      ]
    },
    {
      "id": 6,
      "type": "repeat-and-speak",
      "title": "Colours & Judiciary Vocabulary — Speaking Set 6",
      "sentences": [
        {
          "english": "The witness told the truth.",
          "hindi": "गवाह ने सच बताया।",
          "pronunciation": "the witness told the truth"
        },
        {
          "english": "Evidence was presented in the court.",
          "hindi": "सबूत अदालत में पेश किए गए।",
          "pronunciation": "evidence was presented in the court"
        },
        {
          "english": "The trial went on for three years.",
          "hindi": "मुकदमा तीन साल चला।",
          "pronunciation": "the trial went on for three years"
        }
      ]
    },
    {
      "id": 7,
      "type": "repeat-and-speak",
      "title": "Colours & Judiciary Vocabulary — Speaking Set 7",
      "sentences": [
        {
          "english": "The jury made the decision.",
          "hindi": "जूरी ने फैसला किया।",
          "pronunciation": "the jury made the decision"
        },
        {
          "english": "The court found the accused guilty.",
          "hindi": "अदालत ने आरोपी को दोषी पाया।",
          "pronunciation": "the court found the accused guilty"
        }
      ]
    }
  ]
}
