{
  "day": 74,
  "title": "Grammar + Vocabulary + Speaking Full Revision",
  "tagline": "Grammar + Vocabulary + Speaking Full Revision को सही तरीके से समझें और बोलें।",
  "summary": "Grammar + Vocabulary + Speaking Full Revision का सही उपयोग आपकी English को ज़्यादा natural और fluent बनाता है। Formula: Mixed revision of tenses, modals, conditionals, reported speech, vocabulary and speaking confidence",
  "hindiSummary": "आज आप Grammar + Vocabulary + Speaking Full Revision का सही उपयोग सीखेंगे — कब और कैसे इसे बोलचाल और लेखन में use करना है।",
  "whatYouWillLearn": [
    "Grammar + Vocabulary + Speaking Full Revision की सही formula और structure",
    "Grammar + Vocabulary + Speaking Full Revision के साथ positive, negative और question sentences",
    "Grammar + Vocabulary + Speaking Full Revision का daily life और office में उपयोग",
    "Common mistakes जो लोग यहां करते हैं"
  ]
}
